nornir_table_inventory/__init__.py
nornir_table_inventory/plugins/inventory/__init__.py
nornir_table_inventory/plugins/inventory/table.py
nornir_table_inventory-0.4.5.dist-info/entry_points.txt
nornir_table_inventory-0.4.5.dist-info/LICENSE
nornir_table_inventory-0.4.5.dist-info/WHEEL
nornir_table_inventory-0.4.5.dist-info/METADATA
nornir_table_inventory-0.4.5.dist-info/RECORD
