Metadata-Version: 2.1
Name: nornir-table-inventory
Version: 0.4.5
Summary: nornir inventory plugin,support managing inventory by csv or excel file
Home-page: https://github.com/jiujing/nornir_table_inventory
License: Apache-2.0
Keywords: nornir,table,csv,excel,inventory
Author: feifeiflight
Author-email: feifeiflight@126.com
Requires-Python: >=3.7,<4.0
Classifier: License :: OSI Approved :: Apache Software License
Classifier: Programming Language :: Python :: 3
Classifier: Programming Language :: Python :: 3.7
Classifier: Programming Language :: Python :: 3.8
Classifier: Programming Language :: Python :: 3.9
Classifier: Programming Language :: Python :: 3.10
Classifier: Programming Language :: Python :: 3.11
Classifier: Programming Language :: Python :: 3
Classifier: Programming Language :: Python :: 3.6
Classifier: Programming Language :: Python :: 3.7
Classifier: Programming Language :: Python :: 3.8
Classifier: Topic :: System :: Networking
Requires-Dist: nornir (>=3.0.0,<4.0.0)
Requires-Dist: pandas (>=1.2.0,<2.0.0)
Project-URL: Repository, https://github.com/jiujing/nornir_table_inventory
